skyalmanac/__init__.py
skyalmanac/__main__.py
skyalmanac/astro-data/__init__.py
skyalmanac/astro-data/de421.bsp
skyalmanac/astro-data/hip_main.dat
skyalmanac/data/A4chart0-180_P.pdf
skyalmanac/data/A4chart180-360_P.pdf
skyalmanac/data/Ra.jpg
skyalmanac/data/__init__.py
skyalmanac/data/croppedmoon.png
skyalmanac/docs/Explanation.pdf
skyalmanac/docs/__init__.py
skyalmanac/lib/__init__.py
skyalmanac/lib/alma_skyfield.py
skyalmanac/lib/config.py
skyalmanac/lib/eventtables.py
skyalmanac/lib/increments.py
skyalmanac/lib/ld_charts.py
skyalmanac/lib/ld_skyfield.py
skyalmanac/lib/ld_stardata.py
skyalmanac/lib/ld_tables.py
skyalmanac/lib/mp_eventtables.py
skyalmanac/lib/mp_nautical.py
skyalmanac/lib/nautical.py
skyalmanac/lib/suntables.py
skyalmanac-1.12.5.dist-info/LICENSE
skyalmanac-1.12.5.dist-info/METADATA
skyalmanac-1.12.5.dist-info/WHEEL
skyalmanac-1.12.5.dist-info/top_level.txt
skyalmanac-1.12.5.dist-info/RECORD
