Metadata-Version: 2.1
Name: skyalmanac
Version: 1.12.5
Summary: Creates the daily pages of a Nautical Almanac using Skyfield
Home-page: https://github.com/aendie/SkyAlmanac-Py3
Author: Andrew Bauer
Author-email: aendie.bauer@gmail.com
License: GPL-3.0 License
Classifier: Natural Language :: English
Classifier: Operating System :: OS Independent
Classifier: Development Status :: 5 - Production/Stable
Classifier: License :: OSI Approved :: GNU General Public License v3 (GPLv3)
Classifier: Programming Language :: Python :: 3
Classifier: Programming Language :: Python :: 3.4
Classifier: Programming Language :: Python :: 3.5
Classifier: Programming Language :: Python :: 3.6
Classifier: Programming Language :: Python :: 3.7
Classifier: Programming Language :: Python :: 3.8
Classifier: Programming Language :: Python :: 3.9
Classifier: Programming Language :: Python :: 3.10
Classifier: Programming Language :: Python :: 3.11
Classifier: Programming Language :: Python :: 3.12
Classifier: Programming Language :: Python :: 3.13
Classifier: Topic :: Scientific/Engineering :: Astronomy
Requires-Python: >=3.4
License-File: LICENSE
Requires-Dist: Pandas
Requires-Dist: Skyfield>=1.44
